upb_lib/__init__.py
upb_lib/connection.py
upb_lib/const.py
upb_lib/devices.py
upb_lib/elements.py
upb_lib/links.py
upb_lib/message.py
upb_lib/notify.py
upb_lib/parse_upstart.py
upb_lib/upb.py
upb_lib/util.py
upb_lib-0.6.1.dist-info/METADATA
upb_lib-0.6.1.dist-info/WHEEL
upb_lib-0.6.1.dist-info/licenses/LICENCE
upb_lib-0.6.1.dist-info/RECORD
