Metadata-Version: 2.4
Name: upb-lib
Version: 0.6.1
Summary: Library for interacting with UPB PIM.
Project-URL: Homepage, https://github.com/gwww/upb-lib
Project-URL: Repository, https://github.com/gwww/upb-lib.git
Project-URL: Issues, https://github.com/gwww/upb-lib/issues
Author-email: Glenn Waters <gwwaters+upb-lib@gmail.com>
License-File: LICENCE
Classifier: Development Status :: 5 - Production/Stable
Classifier: Intended Audience :: Developers
Classifier: License :: OSI Approved :: MIT License
Classifier: Programming Language :: Python :: 3.11
Classifier: Programming Language :: Python :: 3.12
Classifier: Programming Language :: Python :: 3.13
Classifier: Topic :: Home Automation
Requires-Python: >=3.11
Requires-Dist: pyserial-asyncio-fast>=0.11
Requires-Dist: pytz>=2021
